spatioloji/__init__.py
spatioloji/data/Spatial_Object.py
spatioloji/data/__init__.py
spatioloji/pl/Plot_Spatial_Image.py
spatioloji/pl/Plot_Spatial_Stat.py
spatioloji/pl/__init__.py
spatioloji/tl/Gene_Set_function.py
spatioloji/tl/Spatial_function.py
spatioloji/tl/__init__.py
spatioloji/utils/__init__.py
spatioloji-0.2.6.dist-info/licenses/LICENSE
spatioloji-0.2.6.dist-info/METADATA
spatioloji-0.2.6.dist-info/WHEEL
spatioloji-0.2.6.dist-info/top_level.txt
spatioloji-0.2.6.dist-info/RECORD
