Metadata-Version: 2.4
Name: SpatioloJI
Version: 0.2.6
Summary: Core foundation for Ji Universe
Author-email: Ji Wang <gynecoloji@gmail.com>
License: MIT
Project-URL: Homepage, https://github.com/gynecoloji/SpatioloJI
Project-URL: Bug Tracker, https://github.com/gynecoloji/SpatioloJI/issues
Classifier: Programming Language :: Python :: 3
Classifier: License :: OSI Approved :: MIT License
Classifier: Operating System :: OS Independent
Requires-Python: >=3.12
License-File: LICENSE
Requires-Dist: anndata==0.11.4
Requires-Dist: matplotlib==3.10.3
Requires-Dist: networkx==3.2.1
Requires-Dist: numpy==2.2.6
Requires-Dist: opencv_python==4.11.0.86
Requires-Dist: pandas==2.2.3
Requires-Dist: scanpy==1.11.1
Requires-Dist: scipy==1.15.3
Requires-Dist: seaborn==0.13.2
Requires-Dist: setuptools==78.1.1
Requires-Dist: Shapely==2.1.0
Requires-Dist: tqdm==4.67.1
Dynamic: license-file
